{
  "METALS_2025-12-22": "2025-12-22 02:35:08",
  "📊 20251222 全市場信用交易統計\n融資(交易單位)\n  前日餘額：7,680,380\n  今日餘額：7,690,065\n  增減數：+9,685\n  增減百分比：+0.13%\n\n融券(交易單位)\n  前日餘額：301,842\n  今日餘額：281,725\n  增減數：-20,117\n  增減百分比：-6.66%\n\n融資金額(仟元)\n  前日餘額：333,308,737\n  今日餘額：335,196,079\n  增減數：+1,887,342\n  增減百分比：+0.57%\n": "2025-12-22 13:09:09",
  "METALS_2025-12-23": "2025-12-23 13:10:49",
  "📊 20251223 全市場信用交易統計\n融資(交易單位)\n  前日餘額：7,690,057\n  今日餘額：7,710,195\n  增減數：+20,138\n  增減百分比：+0.26%\n\n融券(交易單位)\n  前日餘額：281,725\n  今日餘額：279,705\n  增減數：-2,020\n  增減百分比：-0.72%\n\n融資金額(仟元)\n  前日餘額：335,196,079\n  今日餘額：337,588,452\n  增減數：+2,392,373\n  增減百分比：+0.71%\n": "2025-12-23 13:10:49",
  "METALS_2025-12-24": "2025-12-24 13:08:15",
  "📊 20251224 全市場信用交易統計\n融資(交易單位)\n  前日餘額：7,710,188\n  今日餘額：7,739,580\n  增減數：+29,392\n  增減百分比：+0.38%\n\n融券(交易單位)\n  前日餘額：279,705\n  今日餘額：290,092\n  增減數：+10,387\n  增減百分比：+3.71%\n\n融資金額(仟元)\n  前日餘額：337,588,452\n  今日餘額：338,902,814\n  增減數：+1,314,362\n  增減百分比：+0.39%\n": "2025-12-24 13:08:15",
  "METALS_2025-12-25": "2025-12-25 13:08:06",
  "METALS_2025-12-26": "2025-12-26 13:08:26",
  "📊 20251226 全市場信用交易統計\n融資(交易單位)\n  前日餘額：7,739,572\n  今日餘額：7,801,489\n  增減數：+61,917\n  增減百分比：+0.80%\n\n融券(交易單位)\n  前日餘額：290,092\n  今日餘額：305,768\n  增減數：+15,676\n  增減百分比：+5.40%\n\n融資金額(仟元)\n  前日餘額：338,902,814\n  今日餘額：340,337,126\n  增減數：+1,434,312\n  增減百分比：+0.42%\n": "2025-12-26 13:08:26",
  "📊 20251229 全市場信用交易統計\n融資(交易單位)\n  前日餘額：7,801,477\n  今日餘額：7,793,645\n  增減數：-7,832\n  增減百分比：-0.10%\n\n融券(交易單位)\n  前日餘額：305,768\n  今日餘額：306,845\n  增減數：+1,077\n  增減百分比：+0.35%\n\n融資金額(仟元)\n  前日餘額：340,337,182\n  今日餘額：339,886,882\n  增減數：-450,300\n  增減百分比：-0.13%\n": "2025-12-29 13:12:12",
  "METALS_2025-12-30": "2025-12-30 13:11:03",
  "📊 20251230 全市場信用交易統計\n融資(交易單位)\n  前日餘額：7,793,638\n  今日餘額：7,813,048\n  增減數：+19,410\n  增減百分比：+0.25%\n\n融券(交易單位)\n  前日餘額：306,845\n  今日餘額：312,563\n  增減數：+5,718\n  增減百分比：+1.86%\n\n融資金額(仟元)\n  前日餘額：339,886,882\n  今日餘額：341,367,756\n  增減數：+1,480,874\n  增減百分比：+0.44%\n": "2025-12-30 13:11:03",
  "METALS_2025-12-31": "2025-12-31 13:08:57",
  "📊 20251231 全市場信用交易統計\n融資(交易單位)\n  前日餘額：7,813,041\n  今日餘額：7,898,473\n  增減數：+85,432\n  增減百分比：+1.09%\n\n融券(交易單位)\n  前日餘額：312,563\n  今日餘額：313,936\n  增減數：+1,373\n  增減百分比：+0.44%\n\n融資金額(仟元)\n  前日餘額：341,367,697\n  今日餘額：343,409,624\n  增減數：+2,041,927\n  增減百分比：+0.60%\n": "2025-12-31 13:08:57",
  "METALS_2026-01-01": "2026-01-01 13:09:21",
  "METALS_2026-01-02": "2026-01-02 13:08:12",
  "📊 20260102 全市場信用交易統計\n融資(交易單位)\n  前日餘額：7,898,471\n  今日餘額：7,909,125\n  增減數：+10,654\n  增減百分比：+0.13%\n\n融券(交易單位)\n  前日餘額：313,936\n  今日餘額：325,390\n  增減數：+11,454\n  增減百分比：+3.65%\n\n融資金額(仟元)\n  前日餘額：343,409,624\n  今日餘額：346,634,298\n  增減數：+3,224,674\n  增減百分比：+0.94%\n": "2026-01-02 13:08:12",
  "📊 20260105 全市場信用交易統計\n融資(交易單位)\n  前日餘額：7,908,960\n  今日餘額：7,961,892\n  增減數：+52,932\n  增減百分比：+0.67%\n\n融券(交易單位)\n  前日餘額：325,390\n  今日餘額：327,346\n  增減數：+1,956\n  增減百分比：+0.60%\n\n融資金額(仟元)\n  前日餘額：346,633,323\n  今日餘額：350,948,272\n  增減數：+4,314,949\n  增減百分比：+1.24%\n": "2026-01-05 13:14:03",
  "METALS_2026-01-06": "2026-01-06 13:11:33",
  "📊 20260106 全市場信用交易統計\n融資(交易單位)\n  前日餘額：7,961,884\n  今日餘額：8,016,413\n  增減數：+54,529\n  增減百分比：+0.68%\n\n融券(交易單位)\n  前日餘額：327,346\n  今日餘額：353,904\n  增減數：+26,558\n  增減百分比：+8.11%\n\n融資金額(仟元)\n  前日餘額：350,948,272\n  今日餘額：354,549,156\n  增減數：+3,600,884\n  增減百分比：+1.03%\n": "2026-01-06 13:11:33",
  "METALS_2026-01-07": "2026-01-07 13:12:51",
  "📊 20260107 全市場信用交易統計\n融資(交易單位)\n  前日餘額：8,016,403\n  今日餘額：8,060,753\n  增減數：+44,350\n  增減百分比：+0.55%\n\n融券(交易單位)\n  前日餘額：353,904\n  今日餘額：344,163\n  增減數：-9,741\n  增減百分比：-2.75%\n\n融資金額(仟元)\n  前日餘額：354,550,416\n  今日餘額：357,058,834\n  增減數：+2,508,418\n  增減百分比：+0.71%\n": "2026-01-07 13:12:51",
  "METALS_2026-01-08": "2026-01-08 13:13:42",
  "📊 20260108 全市場信用交易統計\n融資(交易單位)\n  前日餘額：8,060,747\n  今日餘額：7,994,320\n  增減數：-66,427\n  增減百分比：-0.82%\n\n融券(交易單位)\n  前日餘額：344,163\n  今日餘額：341,763\n  增減數：-2,400\n  增減百分比：-0.70%\n\n融資金額(仟元)\n  前日餘額：357,058,834\n  今日餘額：352,387,558\n  增減數：-4,671,276\n  增減百分比：-1.31%\n": "2026-01-08 13:13:42",
  "METALS_2026-01-09": "2026-01-09 13:12:35",
  "📊 20260109 全市場信用交易統計\n融資(交易單位)\n  前日餘額：7,994,309\n  今日餘額：7,949,600\n  增減數：-44,709\n  增減百分比：-0.56%\n\n融券(交易單位)\n  前日餘額：341,763\n  今日餘額：317,258\n  增減數：-24,505\n  增減百分比：-7.17%\n\n融資金額(仟元)\n  前日餘額：352,387,651\n  今日餘額：351,492,667\n  增減數：-894,984\n  增減百分比：-0.25%\n": "2026-01-09 13:12:35",
  "📊 20260112 全市場信用交易統計\n融資(交易單位)\n  前日餘額：7,949,477\n  今日餘額：8,058,859\n  增減數：+109,382\n  增減百分比：+1.38%\n\n融券(交易單位)\n  前日餘額：317,258\n  今日餘額：319,182\n  增減數：+1,924\n  增減百分比：+0.61%\n\n融資金額(仟元)\n  前日餘額：351,492,592\n  今日餘額：356,489,999\n  增減數：+4,997,407\n  增減百分比：+1.42%\n": "2026-01-12 13:22:45",
  "METALS_2026-01-13": "2026-01-13 13:22:25",
  "📊 20260113 全市場信用交易統計\n融資(交易單位)\n  前日餘額：8,058,846\n  今日餘額：7,998,293\n  增減數：-60,553\n  增減百分比：-0.75%\n\n融券(交易單位)\n  前日餘額：319,182\n  今日餘額：326,559\n  增減數：+7,377\n  增減百分比：+2.31%\n\n融資金額(仟元)\n  前日餘額：356,490,039\n  今日餘額：355,638,826\n  增減數：-851,213\n  增減百分比：-0.24%\n": "2026-01-13 13:22:25",
  "METALS_2026-01-14": "2026-01-14 13:15:32",
  "115/01/14\n上櫃股票亞泰金屬(證券代號：6727)、竹陞科技(證券代號：6739) 、濾能(證券代號：6823)及夠麻吉(證券代號：8472)自115年1月15日起得為融資融券交易。": "2026-01-14 13:15:32",
  "📊 20260114 全市場信用交易統計\n融資(交易單位)\n  前日餘額：7,998,290\n  今日餘額：8,040,168\n  增減數：+41,878\n  增減百分比：+0.52%\n\n融券(交易單位)\n  前日餘額：326,559\n  今日餘額：323,345\n  增減數：-3,214\n  增減百分比：-0.98%\n\n融資金額(仟元)\n  前日餘額：355,638,826\n  今日餘額：358,452,806\n  增減數：+2,813,980\n  增減百分比：+0.79%\n": "2026-01-14 13:15:32",
  "METALS_2026-01-15": "2026-01-15 13:13:34",
  "📊 20260115 全市場信用交易統計\n融資(交易單位)\n  前日餘額：8,040,156\n  今日餘額：8,045,393\n  增減數：+5,237\n  增減百分比：+0.07%\n\n融券(交易單位)\n  前日餘額：323,345\n  今日餘額：337,855\n  增減數：+14,510\n  增減百分比：+4.49%\n\n融資金額(仟元)\n  前日餘額：358,452,806\n  今日餘額：359,299,228\n  增減數：+846,422\n  增減百分比：+0.24%\n": "2026-01-15 13:13:34",
  "METALS_2026-01-16": "2026-01-16 13:12:11",
  "📊 20260116 全市場信用交易統計\n融資(交易單位)\n  前日餘額：8,045,385\n  今日餘額：8,129,811\n  增減數：+84,426\n  增減百分比：+1.05%\n\n融券(交易單位)\n  前日餘額：337,855\n  今日餘額：321,614\n  增減數：-16,241\n  增減百分比：-4.81%\n\n融資金額(仟元)\n  前日餘額：359,299,228\n  今日餘額：363,391,797\n  增減數：+4,092,569\n  增減百分比：+1.14%\n": "2026-01-16 13:12:11",
  "METALS_2026-01-19": "2026-01-19 13:25:48",
  "📊 20260119 全市場信用交易統計\n融資(交易單位)\n  前日餘額：8,129,796\n  今日餘額：8,245,019\n  增減數：+115,223\n  增減百分比：+1.42%\n\n融券(交易單位)\n  前日餘額：321,614\n  今日餘額：315,084\n  增減數：-6,530\n  增減百分比：-2.03%\n\n融資金額(仟元)\n  前日餘額：363,391,797\n  今日餘額：369,415,656\n  增減數：+6,023,859\n  增減百分比：+1.66%\n": "2026-01-19 13:25:48",
  "📊 20260120 全市場信用交易統計\n融資(交易單位)\n  前日餘額：8,245,037\n  今日餘額：8,214,287\n  增減數：-30,750\n  增減百分比：-0.37%\n\n融券(交易單位)\n  前日餘額：315,084\n  今日餘額：312,100\n  增減數：-2,984\n  增減百分比：-0.95%\n\n融資金額(仟元)\n  前日餘額：369,415,656\n  今日餘額：371,225,738\n  增減數：+1,810,082\n  增減百分比：+0.49%\n": "2026-01-20 13:26:41",
  "METALS_2026-01-21": "2026-01-21 13:25:46",
  "115/01/21\n上櫃股票億而得（代號：6423）及上櫃指數股票型基金受益憑證野村10+澳洲公債（代號：00987B）自115年1月22日起得為融資融券交易。": "2026-01-21 13:25:46",
  "📊 20260121 全市場信用交易統計\n融資(交易單位)\n  前日餘額：8,214,278\n  今日餘額：8,151,017\n  增減數：-63,261\n  增減百分比：-0.77%\n\n融券(交易單位)\n  前日餘額：312,100\n  今日餘額：313,098\n  增減數：+998\n  增減百分比：+0.32%\n\n融資金額(仟元)\n  前日餘額：371,225,738\n  今日餘額：367,750,150\n  增減數：-3,475,588\n  增減百分比：-0.94%\n": "2026-01-21 13:25:46",
  "METALS_2026-01-22": "2026-01-22 13:26:14",
  "📊 20260122 全市場信用交易統計\n融資(交易單位)\n  前日餘額：8,150,908\n  今日餘額：8,193,993\n  增減數：+43,085\n  增減百分比：+0.53%\n\n融券(交易單位)\n  前日餘額：313,084\n  今日餘額：311,678\n  增減數：-1,406\n  增減百分比：-0.45%\n\n融資金額(仟元)\n  前日餘額：367,745,249\n  今日餘額：371,734,427\n  增減數：+3,989,178\n  增減百分比：+1.08%\n": "2026-01-22 13:26:14",
  "METALS_2026-01-23": "2026-01-23 13:23:46",
  "115/01/23\n上櫃指數股票型基金受益憑證大華美國MAG7+（代號：009815）自115年1月26日起得為融資融券交易。": "2026-01-23 13:23:46",
  "📊 20260123 全市場信用交易統計\n融資(交易單位)\n  前日餘額：8,193,989\n  今日餘額：8,205,892\n  增減數：+11,903\n  增減百分比：+0.15%\n\n融券(交易單位)\n  前日餘額：311,678\n  今日餘額：297,936\n  增減數：-13,742\n  增減百分比：-4.41%\n\n融資金額(仟元)\n  前日餘額：371,734,424\n  今日餘額：376,076,978\n  增減數：+4,342,554\n  增減百分比：+1.17%\n": "2026-01-23 13:23:46",
  "📊 20260126 全市場信用交易統計\n融資(交易單位)\n  前日餘額：8,205,889\n  今日餘額：8,288,709\n  增減數：+82,820\n  增減百分比：+1.01%\n\n融券(交易單位)\n  前日餘額：297,939\n  今日餘額：305,432\n  增減數：+7,493\n  增減百分比：+2.51%\n\n融資金額(仟元)\n  前日餘額：376,076,978\n  今日餘額：381,580,658\n  增減數：+5,503,680\n  增減百分比：+1.46%\n": "2026-01-26 13:25:15",
  "METALS_2026-01-27": "2026-01-27 13:27:07",
  "📊 20260127 全市場信用交易統計\n融資(交易單位)\n  前日餘額：8,288,703\n  今日餘額：8,273,625\n  增減數：-15,078\n  增減百分比：-0.18%\n\n融券(交易單位)\n  前日餘額：305,432\n  今日餘額：299,727\n  增減數：-5,705\n  增減百分比：-1.87%\n\n融資金額(仟元)\n  前日餘額：381,580,658\n  今日餘額：382,728,015\n  增減數：+1,147,357\n  增減百分比：+0.30%\n": "2026-01-27 13:27:07",
  "METALS_2026-01-28": "2026-01-28 13:27:59",
  "📊 20260128 全市場信用交易統計\n融資(交易單位)\n  前日餘額：8,273,621\n  今日餘額：8,278,236\n  增減數：+4,615\n  增減百分比：+0.06%\n\n融券(交易單位)\n  前日餘額：299,727\n  今日餘額：304,760\n  增減數：+5,033\n  增減百分比：+1.68%\n\n融資金額(仟元)\n  前日餘額：382,728,165\n  今日餘額：384,920,473\n  增減數：+2,192,308\n  增減百分比：+0.57%\n": "2026-01-28 13:27:59"
}